hexdoc_hexcasting/__gradle_version__.py
hexdoc_hexcasting/__init__.py
hexdoc_hexcasting/__version__.py
hexdoc_hexcasting/_hooks.py
hexdoc_hexcasting/metadata.py
hexdoc_hexcasting/py.typed
hexdoc_hexcasting/_export/__init__.py
hexdoc_hexcasting/_export/generated/__init__.py
hexdoc_hexcasting/_export/generated/hexcasting.hexdoc.json
hexdoc_hexcasting/_export/generated/hexcasting.patterns.hexdoc.json
hexdoc_hexcasting/_export/generated/assets/farmersdelight/lang/en_us.json
hexdoc_hexcasting/_export/generated/assets/farmersdelight/lang/ru_ru.json
hexdoc_hexcasting/_export/generated/assets/farmersdelight/lang/zh_cn.json
hexdoc_hexcasting/_export/generated/assets/farmersdelight/models/block/skillet.json
hexdoc_hexcasting/_export/generated/assets/farmersdelight/models/item/skillet.json
hexdoc_hexcasting/_export/generated/assets/farmersdelight/textures/block/skillet_bottom.png
hexdoc_hexcasting/_export/generated/assets/farmersdelight/textures/block/skillet_side.png
hexdoc_hexcasting/_export/generated/assets/farmersdelight/textures/block/skillet_top.png
hexdoc_hexcasting/_export/generated/assets/hexcasting/lang/en_us.flatten.json5
hexdoc_hexcasting/_export/generated/assets/hexcasting/lang/ru_ru.flatten.json5
hexdoc_hexcasting/_export/generated/assets/hexcasting/lang/zh_cn.flatten.json5
hexdoc_hexcasting/_export/generated/assets/hexcasting/models/block/akashic_bookshelf_empty.json
hexdoc_hexcasting/_export/generated/assets/hexcasting/models/block/akashic_ligature.json
hexdoc_hexcasting/_export/generated/assets/hexcasting/models/block/akashic_record.json
hexdoc_hexcasting/_export/generated/assets/hexcasting/models/block/amethyst_dust_block.json
hexdoc_hexcasting/_export/generated/assets/hexcasting/models/block/amethyst_edified_leaves.json
hexdoc_hexcasting/_export/generated/assets/hexcasting/models/block/amethyst_sconce.json
hexdoc_hexcasting/_export/generated/assets/hexcasting/models/block/ancient_scroll_paper.json
hexdoc_hexcasting-0.11.2.1.0.dist-info/METADATA
hexdoc_hexcasting-0.11.2.1.0.dist-info/WHEEL
hexdoc_hexcasting-0.11.2.1.0.dist-info/entry_points.txt
hexdoc_hexcasting-0.11.2.1.0.dist-info/licenses/LICENSE.txt
hexdoc_hexcasting-0.11.2.1.0.dist-info/RECORD
