Metadata-Version: 2.3
Name: hexdoc-hexcasting
Version: 0.11.2.1.0
Summary: Hex Casting web book.
Project-URL: Homepage, https://hexcasting.hexxy.media/
Project-URL: Source, https://github.com/FallingColors/HexMod/
Author: object-Object, Alwinfy
License: MIT License
Keywords: hexdoc
Requires-Python: >=3.11
Requires-Dist: hexdoc-minecraft~=1.20.1.1.0.dev0
Requires-Dist: hexdoc~=1!0.1.0a11
Provides-Extra: dev
Requires-Dist: ruff~=0.1.4; extra == 'dev'
